Metadata-Version: 2.1
Name: dbleupy
Version: 2.1.2
Summary: This package offers you a more user friendly and easier way to interact with the discord-botlist.eu HTTP api.
Home-page: https://github.com/dbleu/python-library
Author: Florent Tahiri
Author-email: florent.tahiri@gski.de
License: MIT
Keywords: dbleupy api http
Platform: UNKNOWN
Classifier: Development Status :: 5 - Production/Stable
Classifier: License :: OSI Approved :: MIT License
Classifier: Intended Audience :: Developers
Classifier: Natural Language :: English
Classifier: Operating System :: OS Independent
Classifier: Programming Language :: Python :: 3.8
Classifier: Programming Language :: Python :: 3.9
Classifier: Topic :: Internet
Classifier: Topic :: Software Development :: Libraries
Classifier: Topic :: Software Development :: Libraries :: Python Modules
Classifier: Topic :: Utilities
Classifier: Typing :: Typed
Requires-Python: >=3.4.0
License-File: LICENCE.txt
